files3/InfoPackage.py
files3/PfBool.py
files3/Singleton.py
files3/__init__.py
files3/a.py
files3/basic_files.py
files3/ex_files.py
files3/files.py
files3/pycrypt.py
files3/pyfile_shell.py
udsp-0.2.0.dist-info/METADATA
udsp-0.2.0.dist-info/WHEEL
udsp-0.2.0.dist-info/top_level.txt
udsp-0.2.0.dist-info/RECORD
